{
  "required": true,
  "package": "com.fqf.mario_qua_mario.mixin.client",
  "compatibilityLevel": "JAVA_21",
  "client": [
    "AbstractClientPlayerEntityMarioDataMixin",
    "BipedEntityModelMixin",
    "SodiumLevelSliceMixin",
    "CameraMixin",
    "ChunkRendererRegionMixin",
    "ClientPlayerEntityMarioDataMixin",
    "ClientPlayerEntityMixin",
    "ClientPlayNetworkHandlerMixin",
    "CPMClientBaseMixin",
    "GameRendererMixin",
    "HeldItemRendererMixin",
    "InGameHudMixin",
    "MinecraftClientMixin",
    "OtherClientPlayerEntityMarioDataMixin",
    "PlayerEntityModelMixin",
    "PlayerEntityRendererMixin",
    "WorldRendererMixin"
  ],
  "injectors": {
    "defaultRequire": 1
  }
}